py_blk_hash_db/__init__.py
py_blk_hash_db/__main__.py
py_blk_hash_db/mylog.py
py_blk_bash_db-0.0.1.dist-info/LICENSE
py_blk_bash_db-0.0.1.dist-info/METADATA
py_blk_bash_db-0.0.1.dist-info/WHEEL
py_blk_bash_db-0.0.1.dist-info/top_level.txt
py_blk_bash_db-0.0.1.dist-info/RECORD
