Metadata-Version: 2.1
Name: py_blk_bash_db
Version: 0.0.1
Summary: split large file into 1MB small files.
Author-email: GGN_2015 <premierbob@qq.com>
License:                     GNU GENERAL PUBLIC LICENSE
Requires-Python: >=3.12
License-File: LICENSE
